{"year":2018,"scope":"congressional","contest_type":"treasurer","meta":{"source":"precinct_bridge_crosswalk","match_coverage_pct":9.977136454753358,"crosswalk_dir":"crosswalks_cd118_from_2008_t0.005"},"general":{"results":{"1":{"dem_votes":2854.931092910087,"rep_votes":1334.4003389091106,"other_votes":145.50115058689647,"total_votes":4334.832582406094,"dem_candidate":"Dave Young","rep_candidate":"Brian Watson","margin":-1520.5307540009765,"margin_pct":-36.29530818335595,"winner":"DEM","color":"D"},"2":{"dem_votes":31988,"rep_votes":11512,"other_votes":841,"total_votes":44341,"dem_candidate":"Dave Young","rep_candidate":"Brian Watson","margin":-20476,"margin_pct":-47.07126436781609,"winner":"DEM","color":"D"},"3":{"dem_votes":7246,"rep_votes":7330,"other_votes":580,"total_votes":15156,"dem_candidate":"Dave Young","rep_candidate":"Brian Watson","margin":84,"margin_pct":0.5762897914379802,"winner":"REP","color":"R"},"4":{"dem_votes":650.0111650383839,"rep_votes":345.22596018730553,"other_votes":47.34527453997333,"total_votes":1042.5823997656628,"dem_candidate":"Dave Young","rep_candidate":"Brian Watson","margin":-304.78520485107833,"margin_pct":-30.624380574826564,"winner":"DEM","color":"D"},"5":{"dem_votes":63950.988834961616,"rep_votes":97922.77403981269,"other_votes":5023.654725460026,"total_votes":166897.41760023433,"dem_candidate":"Dave Young","rep_candidate":"Brian Watson","margin":33971.785204851076,"margin_pct":20.98659140402616,"winner":"REP","color":"R"},"6":{"dem_votes":853.9858339471845,"rep_votes":694.4450678392265,"other_votes":39.70781379500492,"total_votes":1588.138715581416,"dem_candidate":"Dave Young","rep_candidate":"Brian Watson","margin":-159.540766107958,"margin_pct":-10.303382987506723,"winner":"DEM","color":"D"},"7":{"dem_votes":38.0830731427287,"rep_votes":31.15459325166296,"other_votes":1.791035618098627,"total_votes":71.02870201249029,"dem_candidate":"Dave Young","rep_candidate":"Brian Watson","margin":-6.9284798910657415,"margin_pct":-10.006807351940097,"winner":"DEM","color":"D"}}}}