{"year":2022,"scope":"state_senate","contest_type":"secretary_of_state","meta":{"source":"openelections_precinct_vtd_crosswalk","crosswalk_dir":"crosswalks_2020_2022","method":"OpenElections precinct rows matched to 2020 VTD GEOIDs, then allocated to target districts with local VTD-to-district weights. Existing DRA VTD outputs are preserved.","match_coverage_pct":88.87654250434046,"allocated_coverage_pct":100,"fallback_votes":0},"general":{"results":{"1":{"dem_votes":24899.96761171741,"rep_votes":50125.10561653008,"other_votes":2707.203428451277,"total_votes":77732.27665669877,"dem_candidate":"Jena Griswold","rep_candidate":"Pam Anderson","margin":25225.138004812674,"margin_pct":32.45130477294316,"winner":"REP","color":"R"},"2":{"dem_votes":27840.53993244103,"rep_votes":36366.987277979024,"other_votes":1858.2204233469486,"total_votes":66065.74763376701,"dem_candidate":"Jena Griswold","rep_candidate":"Pam Anderson","margin":8526.447345537996,"margin_pct":12.906002960572,"winner":"REP","color":"R"},"3":{"dem_votes":35096.9999998642,"rep_votes":29635.99999981537,"other_votes":2173.999999987328,"total_votes":66906.99999966689,"dem_candidate":"Jena Griswold","rep_candidate":"Pam Anderson","margin":-5461.000000048833,"margin_pct":-8.162075717153693,"winner":"DEM","color":"D"},"4":{"dem_votes":64308.302132428864,"rep_votes":73768.6064201544,"other_votes":4246.128902280477,"total_votes":142323.03745486375,"dem_candidate":"Jena Griswold","rep_candidate":"Pam Anderson","margin":9460.304287725543,"margin_pct":6.647064633317553,"winner":"REP","color":"R"},"5":{"dem_votes":33660.41884367487,"rep_votes":29859.52249026368,"other_votes":1942.7787300211223,"total_votes":65462.72006395967,"dem_candidate":"Jena Griswold","rep_candidate":"Pam Anderson","margin":-3800.8963534111863,"margin_pct":-5.8061998488568145,"winner":"DEM","color":"D"},"6":{"dem_votes":42853.74188177557,"rep_votes":39805.34437686663,"other_votes":2919.1394834720872,"total_votes":85578.22574211429,"dem_candidate":"Jena Griswold","rep_candidate":"Pam Anderson","margin":-3048.397504908935,"margin_pct":-3.562118142172203,"winner":"DEM","color":"D"},"7":{"dem_votes":29666.55680447547,"rep_votes":43577.8582934493,"other_votes":2807.7080122874077,"total_votes":76052.12311021217,"dem_candidate":"Jena Griswold","rep_candidate":"Pam Anderson","margin":13911.301488973833,"margin_pct":18.291798992664603,"winner":"REP","color":"R"},"8":{"dem_votes":41417.57444180534,"rep_votes":33215.20961748932,"other_votes":2273.2819447425663,"total_votes":76906.06600403723,"dem_candidate":"Jena Griswold","rep_candidate":"Pam Anderson","margin":-8202.364824316013,"margin_pct":-10.665432846201526,"winner":"DEM","color":"D"},"9":{"dem_votes":29194.693161317373,"rep_votes":43948.88815152629,"other_votes":1904.0145300260276,"total_votes":75047.59584286969,"dem_candidate":"Jena Griswold","rep_candidate":"Pam Anderson","margin":14754.194990208918,"margin_pct":19.659783667288153,"winner":"REP","color":"R"},"10":{"dem_votes":27031.652756742795,"rep_votes":33606.22781737598,"other_votes":2051.8557619885587,"total_votes":62689.73633610733,"dem_candidate":"Jena Griswold","rep_candidate":"Pam Anderson","margin":6574.575060633182,"margin_pct":10.487482393264482,"winner":"REP","color":"R"},"11":{"dem_votes":21075.516883792297,"rep_votes":17145.737859152352,"other_votes":1726.2293710499698,"total_votes":39947.48411399462,"dem_candidate":"Jena Griswold","rep_candidate":"Pam Anderson","margin":-3929.7790246399454,"margin_pct":-9.837363007457192,"winner":"DEM","color":"D"},"12":{"dem_votes":30198.094031607274,"rep_votes":26692.948445882168,"other_votes":1853.6924908723097,"total_votes":58744.73496836175,"dem_candidate":"Jena Griswold","rep_candidate":"Pam Anderson","margin":-3505.145585725106,"margin_pct":-5.96673997697475,"winner":"DEM","color":"D"},"13":{"dem_votes":18643.789325967995,"rep_votes":25358.668529050035,"other_votes":1554.898320942601,"total_votes":45557.35617596063,"dem_candidate":"Jena Griswold","rep_candidate":"Pam Anderson","margin":6714.8792030820405,"margin_pct":14.739396151845394,"winner":"REP","color":"R"},"14":{"dem_votes":44537.24832856274,"rep_votes":24757.663090967875,"other_votes":1806.6719753526052,"total_votes":71101.58339488323,"dem_candidate":"Jena Griswold","rep_candidate":"Pam Anderson","margin":-19779.585237594863,"margin_pct":-27.818768996666655,"winner":"DEM","color":"D"},"15":{"dem_votes":61760.31553974747,"rep_votes":44151.7300746038,"other_votes":3067.099175821901,"total_votes":108979.14479017317,"dem_candidate":"Jena Griswold","rep_candidate":"Pam Anderson","margin":-17608.585465143668,"margin_pct":-16.157757063562002,"winner":"DEM","color":"D"},"16":{"dem_votes":48882.74307277451,"rep_votes":39590.75772099343,"other_votes":2199.025528681937,"total_votes":90672.52632244988,"dem_candidate":"Jena Griswold","rep_candidate":"Pam Anderson","margin":-9291.985351781077,"margin_pct":-10.247850951827342,"winner":"DEM","color":"D"},"17":{"dem_votes":50193.147748454474,"rep_votes":21639.796802521105,"other_votes":1924.4901144908456,"total_votes":73757.43466546643,"dem_candidate":"Jena Griswold","rep_candidate":"Pam Anderson","margin":-28553.35094593337,"margin_pct":-38.712505492415374,"winner":"DEM","color":"D"},"18":{"dem_votes":66685.22994132343,"rep_votes":12858.053249865274,"other_votes":1456.7721847173345,"total_votes":81000.05537590604,"dem_candidate":"Jena Griswold","rep_candidate":"Pam Anderson","margin":-53827.17669145815,"margin_pct":-66.45325912637509,"winner":"DEM","color":"D"},"19":{"dem_votes":40323.65216706298,"rep_votes":27789.423190417234,"other_votes":1842.5528966311708,"total_votes":69955.62825411138,"dem_candidate":"Jena Griswold","rep_candidate":"Pam Anderson","margin":-12534.228976645747,"margin_pct":-17.917398913373486,"winner":"DEM","color":"D"},"20":{"dem_votes":52005.95014394874,"rep_votes":36805.6909067999,"other_votes":2575.66437330448,"total_votes":91387.30542405312,"dem_candidate":"Jena Griswold","rep_candidate":"Pam Anderson","margin":-15200.259237148843,"margin_pct":-16.6327906995583,"winner":"DEM","color":"D"},"21":{"dem_votes":29868.253698283497,"rep_votes":22854.882724602456,"other_votes":2006.8078348971535,"total_votes":54729.94425778311,"dem_candidate":"Jena Griswold","rep_candidate":"Pam Anderson","margin":-7013.3709736810415,"margin_pct":-12.814504141731653,"winner":"DEM","color":"D"},"22":{"dem_votes":39160.17255784909,"rep_votes":25234.864647620907,"other_votes":1750.4341113729106,"total_votes":66145.47131684292,"dem_candidate":"Jena Griswold","rep_candidate":"Pam Anderson","margin":-13925.30791022818,"margin_pct":-21.052549226725848,"winner":"DEM","color":"D"},"23":{"dem_votes":21389.21289065127,"rep_votes":28508.011116558395,"other_votes":1625.4241340009053,"total_votes":51522.648141210564,"dem_candidate":"Jena Griswold","rep_candidate":"Pam Anderson","margin":7118.798225907125,"margin_pct":13.81683295159111,"winner":"REP","color":"R"},"24":{"dem_votes":30481.78099148946,"rep_votes":22815.50469977159,"other_votes":1657.681247502556,"total_votes":54954.96693876361,"dem_candidate":"Jena Griswold","rep_candidate":"Pam Anderson","margin":-7666.27629171787,"margin_pct":-13.950106275671882,"winner":"DEM","color":"D"},"25":{"dem_votes":44045.616309901445,"rep_votes":26728.489638923675,"other_votes":1824.9071144808431,"total_votes":72599.01306330596,"dem_candidate":"Jena Griswold","rep_candidate":"Pam Anderson","margin":-17317.12667097777,"margin_pct":-23.853115821116365,"winner":"DEM","color":"D"},"26":{"dem_votes":39144.55865167866,"rep_votes":20361.83026029274,"other_votes":1448.707532568715,"total_votes":60955.09644454012,"dem_candidate":"Jena Griswold","rep_candidate":"Pam Anderson","margin":-18782.728391385917,"margin_pct":-30.814040969446005,"winner":"DEM","color":"D"},"27":{"dem_votes":38221.038140095654,"rep_votes":29412.750907619757,"other_votes":1677.2742506822776,"total_votes":69311.0632983977,"dem_candidate":"Jena Griswold","rep_candidate":"Pam Anderson","margin":-8808.287232475897,"margin_pct":-12.70834238187127,"winner":"DEM","color":"D"},"28":{"dem_votes":25229.564412926284,"rep_votes":12060.251159819481,"other_votes":1301.429061033536,"total_votes":38591.2446337793,"dem_candidate":"Jena Griswold","rep_candidate":"Pam Anderson","margin":-13169.313253106802,"margin_pct":-34.12513221089421,"winner":"DEM","color":"D"},"29":{"dem_votes":33835.82446945234,"rep_votes":16765.69359225961,"other_votes":1589.869865919588,"total_votes":52191.387927631535,"dem_candidate":"Jena Griswold","rep_candidate":"Pam Anderson","margin":-17070.13087719273,"margin_pct":-32.70679618802653,"winner":"DEM","color":"D"},"30":{"dem_votes":37687.12821123163,"rep_votes":38651.63952037386,"other_votes":1639.6106311563447,"total_votes":77978.37836276184,"dem_candidate":"Jena Griswold","rep_candidate":"Pam Anderson","margin":964.5113091422245,"margin_pct":1.2368958285529335,"winner":"REP","color":"R"},"31":{"dem_votes":71032.3597439963,"rep_votes":16087.538356832405,"other_votes":1441.99764991584,"total_votes":88561.89575074454,"dem_candidate":"Jena Griswold","rep_candidate":"Pam Anderson","margin":-54944.8213871639,"margin_pct":-62.04115316343821,"winner":"DEM","color":"D"},"32":{"dem_votes":38267.60920678821,"rep_votes":12206.164677586272,"other_votes":1211.1539852439225,"total_votes":51684.92786961841,"dem_candidate":"Jena Griswold","rep_candidate":"Pam Anderson","margin":-26061.44452920194,"margin_pct":-50.42368366063147,"winner":"DEM","color":"D"},"33":{"dem_votes":50263.106335562516,"rep_votes":9990.174566443708,"other_votes":1309.2032813022615,"total_votes":61562.48418330849,"dem_candidate":"Jena Griswold","rep_candidate":"Pam Anderson","margin":-40272.931769118804,"margin_pct":-65.41797704134567,"winner":"DEM","color":"D"},"34":{"dem_votes":50156.29713830471,"rep_votes":10738.034717048982,"other_votes":1470.4026270151276,"total_votes":62364.734482368825,"dem_candidate":"Jena Griswold","rep_candidate":"Pam Anderson","margin":-39418.26242125573,"margin_pct":-63.206013379884894,"winner":"DEM","color":"D"},"35":{"dem_votes":29981.34249230395,"rep_votes":62465.9494825427,"other_votes":3289.669024439049,"total_votes":95736.9609992857,"dem_candidate":"Jena Griswold","rep_candidate":"Pam Anderson","margin":32484.606990238753,"margin_pct":33.93110315093574,"winner":"REP","color":"R"}}}}