{"year":2004,"scope":"state_house","contest_type":"us_senate","meta":{"source":"precinct_bridge_crosswalk","match_coverage_pct":9.977136454753358,"crosswalk_dir":"crosswalks_cd118_from_2008_t0.005"},"general":{"results":{"3":{"dem_votes":31,"rep_votes":29,"other_votes":3,"total_votes":63,"dem_candidate":"Ken Salazar","rep_candidate":"Pete Coors","margin":-2,"margin_pct":-3.3333333333333335,"winner":"DEM","color":"D"},"6":{"dem_votes":8.862981551517596,"rep_votes":10.323912576493024,"other_votes":0.2434885041625713,"total_votes":19.430382632173192,"dem_candidate":"Ken Salazar","rep_candidate":"Pete Coors","margin":1.4609310249754284,"margin_pct":7.614213197969545,"winner":"REP","color":"R"},"9":{"dem_votes":1450,"rep_votes":1017,"other_votes":56,"total_votes":2523,"dem_candidate":"Ken Salazar","rep_candidate":"Pete Coors","margin":-433,"margin_pct":-17.55168220510742,"winner":"DEM","color":"D"},"14":{"dem_votes":7050.270746813834,"rep_votes":17700.79721407305,"other_votes":405.48122907989574,"total_votes":25156.549189966776,"dem_candidate":"Ken Salazar","rep_candidate":"Pete Coors","margin":10650.526467259215,"margin_pct":43.03057340430649,"winner":"REP","color":"R"},"15":{"dem_votes":3045.8691802612557,"rep_votes":7026.842995819363,"other_votes":278.4064341069879,"total_votes":10351.118610187606,"dem_candidate":"Ken Salazar","rep_candidate":"Pete Coors","margin":3980.973815558107,"margin_pct":39.522362457765965,"winner":"REP","color":"R"},"16":{"dem_votes":7087.088445427054,"rep_votes":12112.911093841933,"other_votes":537.5970716085053,"total_votes":19737.596610877492,"dem_candidate":"Ken Salazar","rep_candidate":"Pete Coors","margin":5025.822648414879,"margin_pct":26.176160255294622,"winner":"REP","color":"R"},"17":{"dem_votes":5938.475934525731,"rep_votes":7044.009123612969,"other_votes":523.7130407839804,"total_votes":13506.19809892268,"dem_candidate":"Ken Salazar","rep_candidate":"Pete Coors","margin":1105.5331890872385,"margin_pct":8.51557451548293,"winner":"REP","color":"R"},"18":{"dem_votes":8004.730230784875,"rep_votes":13077.531635837964,"other_votes":408.8989003512809,"total_votes":21491.160766974117,"dem_candidate":"Ken Salazar","rep_candidate":"Pete Coors","margin":5072.801405053089,"margin_pct":24.06194096793894,"winner":"REP","color":"R"},"20":{"dem_votes":5601.266403884454,"rep_votes":16248.920856663406,"other_votes":386.8754355097132,"total_votes":22237.062696057572,"dem_candidate":"Ken Salazar","rep_candidate":"Pete Coors","margin":10647.654452778952,"margin_pct":48.7302663625409,"winner":"REP","color":"R"},"21":{"dem_votes":4512.586226528181,"rep_votes":7546.383310900889,"other_votes":422.230771604003,"total_votes":12481.200309033075,"dem_candidate":"Ken Salazar","rep_candidate":"Pete Coors","margin":3033.797084372708,"margin_pct":25.158012672279312,"winner":"REP","color":"R"},"22":{"dem_votes":9730.094510876632,"rep_votes":22744.494695473455,"other_votes":693.4310894406341,"total_votes":33168.020295790724,"dem_candidate":"Ken Salazar","rep_candidate":"Pete Coors","margin":13014.400184596823,"margin_pct":40.07564222568206,"winner":"REP","color":"R"},"42":{"dem_votes":695.1370184484824,"rep_votes":796.6760874235069,"other_votes":21.75651149583743,"total_votes":1513.5696173678268,"dem_candidate":"Ken Salazar","rep_candidate":"Pete Coors","margin":101.53906897502452,"margin_pct":6.8064202261900135,"winner":"REP","color":"R"},"46":{"dem_votes":5085.75628106631,"rep_votes":3909.6919118850687,"other_votes":182.0169004394067,"total_votes":9177.465093390785,"dem_candidate":"Ken Salazar","rep_candidate":"Pete Coors","margin":-1176.0643691812415,"margin_pct":-13.073994135198042,"winner":"DEM","color":"D"},"47":{"dem_votes":461.01505760531364,"rep_votes":566.3818477542991,"other_votes":22.586445728554295,"total_votes":1049.983351088167,"dem_candidate":"Ken Salazar","rep_candidate":"Pete Coors","margin":105.36679014898544,"margin_pct":10.25570445066745,"winner":"REP","color":"R"},"56":{"dem_votes":940.7887963744336,"rep_votes":3101.671231269485,"other_votes":130.33837669754755,"total_votes":4172.798404341466,"dem_candidate":"Ken Salazar","rep_candidate":"Pete Coors","margin":2160.882434895051,"margin_pct":53.4546395046109,"winner":"REP","color":"R"},"60":{"dem_votes":462.1783895288554,"rep_votes":727.6045395820322,"other_votes":22.386977511076356,"total_votes":1212.169906621964,"dem_candidate":"Ken Salazar","rep_candidate":"Pete Coors","margin":265.4261500531768,"margin_pct":22.308787893899858,"winner":"REP","color":"R"},"62":{"dem_votes":2945.8797963230704,"rep_votes":1328.7595432860862,"other_votes":78.03732713841433,"total_votes":4352.676666747571,"dem_candidate":"Ken Salazar","rep_candidate":"Pete Coors","margin":-1617.1202530369842,"margin_pct":-37.83056591588011,"winner":"DEM","color":"D"}}}}