{"rows": [{"county": "Adams", "dem_votes": 55930.0, "rep_votes": 34611.0, "other_votes": 2607.0, "total_votes": 93148.0, "dem_candidate": "Bill Ritter Jr./ Barbara O'Brien", "rep_candidate": "Bob Beauprez/ Janet Rowland", "margin": -21319.0, "margin_pct": -23.546238720579627, "winner": "DEM", "color": "D"}, {"county": "Alamosa", "dem_votes": 3098.0, "rep_votes": 1591.0, "other_votes": 89.0, "total_votes": 4778.0, "dem_candidate": "Bill Ritter Jr./ Barbara O'Brien", "rep_candidate": "Bob Beauprez/ Janet Rowland", "margin": -1507.0, "margin_pct": -32.13904883770527, "winner": "DEM", "color": "D"}, {"county": "Arapahoe", "dem_votes": 98203.0, "rep_votes": 66907.0, "other_votes": 4212.0, "total_votes": 169322.0, "dem_candidate": "Bill Ritter Jr./ Barbara O'Brien", "rep_candidate": "Bob Beauprez/ Janet Rowland", "margin": -31296.0, "margin_pct": -18.95463630307068, "winner": "DEM", "color": "D"}, {"county": "Archuleta", "dem_votes": 2274.0, "rep_votes": 2231.0, "other_votes": 118.0, "total_votes": 4623.0, "dem_candidate": "Bill Ritter Jr./ Barbara O'Brien", "rep_candidate": "Bob Beauprez/ Janet Rowland", "margin": -43.0, "margin_pct": -0.9544950055493896, "winner": "DEM", "color": "D"}, {"county": "Baca", "dem_votes": 783.0, "rep_votes": 1034.0, "other_votes": 52.0, "total_votes": 1869.0, "dem_candidate": "Bill Ritter Jr./ Barbara O'Brien", "rep_candidate": "Bob Beauprez/ Janet Rowland", "margin": 251.0, "margin_pct": 13.813979086406164, "winner": "REP", "color": "R"}, {"county": "Bent", "dem_votes": 910.0, "rep_votes": 662.0, "other_votes": 35.0, "total_votes": 1607.0, "dem_candidate": "Bill Ritter Jr./ Barbara O'Brien", "rep_candidate": "Bob Beauprez/ Janet Rowland", "margin": -248.0, "margin_pct": -15.776081424936386, "winner": "DEM", "color": "D"}, {"county": "Boulder", "dem_votes": 84235.0, "rep_votes": 31003.0, "other_votes": 3093.0, "total_votes": 118331.0, "dem_candidate": "Bill Ritter Jr./ Barbara O'Brien", "rep_candidate": "Bob Beauprez/ Janet Rowland", "margin": -53232.0, "margin_pct": -46.193096027352084, "winner": "DEM", "color": "D"}, {"county": "Broomfield", "dem_votes": 10517.0, "rep_votes": 7544.0, "other_votes": 470.0, "total_votes": 18531.0, "dem_candidate": "Bill Ritter Jr./ Barbara O'Brien", "rep_candidate": "Bob Beauprez/ Janet Rowland", "margin": -2973.0, "margin_pct": -16.460882564642045, "winner": "DEM", "color": "D"}, {"county": "Chaffee", "dem_votes": 4298.0, "rep_votes": 2940.0, "other_votes": 202.0, "total_votes": 7440.0, "dem_candidate": "Bill Ritter Jr./ Barbara O'Brien", "rep_candidate": "Bob Beauprez/ Janet Rowland", "margin": -1358.0, "margin_pct": -18.762088974854933, "winner": "DEM", "color": "D"}, {"county": "Cheyenne", "dem_votes": 339.0, "rep_votes": 598.0, "other_votes": 19.0, "total_votes": 956.0, "dem_candidate": "Bill Ritter Jr./ Barbara O'Brien", "rep_candidate": "Bob Beauprez/ Janet Rowland", "margin": 259.0, "margin_pct": 27.641408751334044, "winner": "REP", "color": "R"}, {"county": "Clear Creek", "dem_votes": 2708.0, "rep_votes": 1516.0, "other_votes": 192.0, "total_votes": 4416.0, "dem_candidate": "Bill Ritter Jr./ Barbara O'Brien", "rep_candidate": "Bob Beauprez/ Janet Rowland", "margin": -1192.0, "margin_pct": -28.219696969696972, "winner": "DEM", "color": "D"}, {"county": "Conejos", "dem_votes": 2063.0, "rep_votes": 1055.0, "other_votes": 75.0, "total_votes": 3193.0, "dem_candidate": "Bill Ritter Jr./ Barbara O'Brien", "rep_candidate": "Bob Beauprez/ Janet Rowland", "margin": -1008.0, "margin_pct": -32.32841565105837, "winner": "DEM", "color": "D"}, {"county": "Costilla", "dem_votes": 1146.0, "rep_votes": 293.0, "other_votes": 33.0, "total_votes": 1472.0, "dem_candidate": "Bill Ritter Jr./ Barbara O'Brien", "rep_candidate": "Bob Beauprez/ Janet Rowland", "margin": -853.0, "margin_pct": -59.277275886031966, "winner": "DEM", "color": "D"}, {"county": "Crowley", "dem_votes": 594.0, "rep_votes": 629.0, "other_votes": 39.0, "total_votes": 1262.0, "dem_candidate": "Bill Ritter Jr./ Barbara O'Brien", "rep_candidate": "Bob Beauprez/ Janet Rowland", "margin": 35.0, "margin_pct": 2.8618152085036797, "winner": "REP", "color": "R"}, {"county": "Custer", "dem_votes": 788.0, "rep_votes": 1042.0, "other_votes": 41.0, "total_votes": 1871.0, "dem_candidate": "Bill Ritter Jr./ Barbara O'Brien", "rep_candidate": "Bob Beauprez/ Janet Rowland", "margin": 254.0, "margin_pct": 13.879781420765028, "winner": "REP", "color": "R"}, {"county": "Delta", "dem_votes": 5078.0, "rep_votes": 5750.0, "other_votes": 496.0, "total_votes": 11324.0, "dem_candidate": "Bill Ritter Jr./ Barbara O'Brien", "rep_candidate": "Bob Beauprez/ Janet Rowland", "margin": 672.0, "margin_pct": 6.20613224972294, "winner": "REP", "color": "R"}, {"county": "Denver", "dem_votes": 121494.0, "rep_votes": 31851.0, "other_votes": 4109.0, "total_votes": 157454.0, "dem_candidate": "Bill Ritter Jr./ Barbara O'Brien", "rep_candidate": "Bob Beauprez/ Janet Rowland", "margin": -89643.0, "margin_pct": -58.45837816687861, "winner": "DEM", "color": "D"}, {"county": "Dolores", "dem_votes": 527.0, "rep_votes": 432.0, "other_votes": 31.0, "total_votes": 990.0, "dem_candidate": "Bill Ritter Jr./ Barbara O'Brien", "rep_candidate": "Bob Beauprez/ Janet Rowland", "margin": -95.0, "margin_pct": -9.906152241918665, "winner": "DEM", "color": "D"}, {"county": "Douglas", "dem_votes": 36364.0, "rep_votes": 42513.0, "other_votes": 1489.0, "total_votes": 80366.0, "dem_candidate": "Bill Ritter Jr./ Barbara O'Brien", "rep_candidate": "Bob Beauprez/ Janet Rowland", "margin": 6149.0, "margin_pct": 7.79568188445301, "winner": "REP", "color": "R"}, {"county": "Eagle", "dem_votes": 8158.0, "rep_votes": 4492.0, "other_votes": 365.0, "total_votes": 13015.0, "dem_candidate": "Bill Ritter Jr./ Barbara O'Brien", "rep_candidate": "Bob Beauprez/ Janet Rowland", "margin": -3666.0, "margin_pct": -28.980237154150196, "winner": "DEM", "color": "D"}, {"county": "El Paso", "dem_votes": 69237.0, "rep_votes": 99629.0, "other_votes": 5232.0, "total_votes": 174098.0, "dem_candidate": "Bill Ritter Jr./ Barbara O'Brien", "rep_candidate": "Bob Beauprez/ Janet Rowland", "margin": 30392.0, "margin_pct": 17.997702320182867, "winner": "REP", "color": "R"}, {"county": "Elbert", "dem_votes": 3134.0, "rep_votes": 5463.0, "other_votes": 223.0, "total_votes": 8820.0, "dem_candidate": "Bill Ritter Jr./ Barbara O'Brien", "rep_candidate": "Bob Beauprez/ Janet Rowland", "margin": 2329.0, "margin_pct": 27.09084564382924, "winner": "REP", "color": "R"}, {"county": "Fremont", "dem_votes": 6768.0, "rep_votes": 6872.0, "other_votes": 423.0, "total_votes": 14063.0, "dem_candidate": "Bill Ritter Jr./ Barbara O'Brien", "rep_candidate": "Bob Beauprez/ Janet Rowland", "margin": 104.0, "margin_pct": 0.7624633431085044, "winner": "REP", "color": "R"}, {"county": "Garfield", "dem_votes": 8602.0, "rep_votes": 6043.0, "other_votes": 526.0, "total_votes": 15171.0, "dem_candidate": "Bill Ritter Jr./ Barbara O'Brien", "rep_candidate": "Bob Beauprez/ Janet Rowland", "margin": -2559.0, "margin_pct": -17.473540457494025, "winner": "DEM", "color": "D"}, {"county": "Gilpin", "dem_votes": 1551.0, "rep_votes": 769.0, "other_votes": 135.0, "total_votes": 2455.0, "dem_candidate": "Bill Ritter Jr./ Barbara O'Brien", "rep_candidate": "Bob Beauprez/ Janet Rowland", "margin": -782.0, "margin_pct": -33.706896551724135, "winner": "DEM", "color": "D"}, {"county": "Grand", "dem_votes": 3149.0, "rep_votes": 2625.0, "other_votes": 165.0, "total_votes": 5939.0, "dem_candidate": "Bill Ritter Jr./ Barbara O'Brien", "rep_candidate": "Bob Beauprez/ Janet Rowland", "margin": -524.0, "margin_pct": -9.075164530654659, "winner": "DEM", "color": "D"}, {"county": "Gunnison", "dem_votes": 4154.0, "rep_votes": 1793.0, "other_votes": 358.0, "total_votes": 6305.0, "dem_candidate": "Bill Ritter Jr./ Barbara O'Brien", "rep_candidate": "Bob Beauprez/ Janet Rowland", "margin": -2361.0, "margin_pct": -39.70068942323861, "winner": "DEM", "color": "D"}, {"county": "Hinsdale", "dem_votes": 252.0, "rep_votes": 220.0, "other_votes": 28.0, "total_votes": 500.0, "dem_candidate": "Bill Ritter Jr./ Barbara O'Brien", "rep_candidate": "Bob Beauprez/ Janet Rowland", "margin": -32.0, "margin_pct": -6.779661016949152, "winner": "DEM", "color": "D"}, {"county": "Huerfano", "dem_votes": 1910.0, "rep_votes": 921.0, "other_votes": 75.0, "total_votes": 2906.0, "dem_candidate": "Bill Ritter Jr./ Barbara O'Brien", "rep_candidate": "Bob Beauprez/ Janet Rowland", "margin": -989.0, "margin_pct": -34.93465206640763, "winner": "DEM", "color": "D"}, {"county": "Jackson", "dem_votes": 302.0, "rep_votes": 417.0, "other_votes": 35.0, "total_votes": 754.0, "dem_candidate": "Bill Ritter Jr./ Barbara O'Brien", "rep_candidate": "Bob Beauprez/ Janet Rowland", "margin": 115.0, "margin_pct": 15.99443671766342, "winner": "REP", "color": "R"}, {"county": "Jefferson", "dem_votes": 119420.0, "rep_votes": 82364.0, "other_votes": 5775.0, "total_votes": 207559.0, "dem_candidate": "Bill Ritter Jr./ Barbara O'Brien", "rep_candidate": "Bob Beauprez/ Janet Rowland", "margin": -37056.0, "margin_pct": -18.364191412599613, "winner": "DEM", "color": "D"}, {"county": "Kiowa", "dem_votes": 313.0, "rep_votes": 479.0, "other_votes": 13.0, "total_votes": 805.0, "dem_candidate": "Bill Ritter Jr./ Barbara O'Brien", "rep_candidate": "Bob Beauprez/ Janet Rowland", "margin": 166.0, "margin_pct": 20.95959595959596, "winner": "REP", "color": "R"}, {"county": "Kit Carson", "dem_votes": 1131.0, "rep_votes": 1592.0, "other_votes": 64.0, "total_votes": 2787.0, "dem_candidate": "Bill Ritter Jr./ Barbara O'Brien", "rep_candidate": "Bob Beauprez/ Janet Rowland", "margin": 461.0, "margin_pct": 16.92985677561513, "winner": "REP", "color": "R"}, {"county": "La Plata", "dem_votes": 11962.0, "rep_votes": 6666.0, "other_votes": 518.0, "total_votes": 19146.0, "dem_candidate": "Bill Ritter Jr./ Barbara O'Brien", "rep_candidate": "Bob Beauprez/ Janet Rowland", "margin": -5296.0, "margin_pct": -28.43031994846468, "winner": "DEM", "color": "D"}, {"county": "Lake", "dem_votes": 1517.0, "rep_votes": 709.0, "other_votes": 111.0, "total_votes": 2337.0, "dem_candidate": "Bill Ritter Jr./ Barbara O'Brien", "rep_candidate": "Bob Beauprez/ Janet Rowland", "margin": -808.0, "margin_pct": -36.298292902066486, "winner": "DEM", "color": "D"}, {"county": "Larimer", "dem_votes": 63297.0, "rep_votes": 45706.0, "other_votes": 3926.0, "total_votes": 112929.0, "dem_candidate": "Bill Ritter Jr./ Barbara O'Brien", "rep_candidate": "Bob Beauprez/ Janet Rowland", "margin": -17591.0, "margin_pct": -16.13808794253369, "winner": "DEM", "color": "D"}, {"county": "Las Animas", "dem_votes": 3243.0, "rep_votes": 1506.0, "other_votes": 119.0, "total_votes": 4868.0, "dem_candidate": "Bill Ritter Jr./ Barbara O'Brien", "rep_candidate": "Bob Beauprez/ Janet Rowland", "margin": -1737.0, "margin_pct": -36.576121288692356, "winner": "DEM", "color": "D"}, {"county": "Lincoln", "dem_votes": 737.0, "rep_votes": 1036.0, "other_votes": 58.0, "total_votes": 1831.0, "dem_candidate": "Bill Ritter Jr./ Barbara O'Brien", "rep_candidate": "Bob Beauprez/ Janet Rowland", "margin": 299.0, "margin_pct": 16.864072194021432, "winner": "REP", "color": "R"}, {"county": "Logan", "dem_votes": 3559.0, "rep_votes": 3832.0, "other_votes": 176.0, "total_votes": 7567.0, "dem_candidate": "Bill Ritter Jr./ Barbara O'Brien", "rep_candidate": "Bob Beauprez/ Janet Rowland", "margin": 273.0, "margin_pct": 3.6936815045325395, "winner": "REP", "color": "R"}, {"county": "Mesa", "dem_votes": 21475.0, "rep_votes": 23471.0, "other_votes": 1753.0, "total_votes": 46699.0, "dem_candidate": "Bill Ritter Jr./ Barbara O'Brien", "rep_candidate": "Bob Beauprez/ Janet Rowland", "margin": 1996.0, "margin_pct": 4.440884617096071, "winner": "REP", "color": "R"}, {"county": "Mineral", "dem_votes": 338.0, "rep_votes": 235.0, "other_votes": 10.0, "total_votes": 583.0, "dem_candidate": "Bill Ritter Jr./ Barbara O'Brien", "rep_candidate": "Bob Beauprez/ Janet Rowland", "margin": -103.0, "margin_pct": -17.975567190226876, "winner": "DEM", "color": "D"}, {"county": "Moffat", "dem_votes": 1750.0, "rep_votes": 2216.0, "other_votes": 194.0, "total_votes": 4160.0, "dem_candidate": "Bill Ritter Jr./ Barbara O'Brien", "rep_candidate": "Bob Beauprez/ Janet Rowland", "margin": 466.0, "margin_pct": 11.749873928391326, "winner": "REP", "color": "R"}, {"county": "Montezuma", "dem_votes": 4146.0, "rep_votes": 4263.0, "other_votes": 197.0, "total_votes": 8606.0, "dem_candidate": "Bill Ritter Jr./ Barbara O'Brien", "rep_candidate": "Bob Beauprez/ Janet Rowland", "margin": 117.0, "margin_pct": 1.3913663931501963, "winner": "REP", "color": "R"}, {"county": "Montrose", "dem_votes": 5639.0, "rep_votes": 6067.0, "other_votes": 535.0, "total_votes": 12241.0, "dem_candidate": "Bill Ritter Jr./ Barbara O'Brien", "rep_candidate": "Bob Beauprez/ Janet Rowland", "margin": 428.0, "margin_pct": 3.6562446608576797, "winner": "REP", "color": "R"}, {"county": "Morgan", "dem_votes": 3419.0, "rep_votes": 4008.0, "other_votes": 185.0, "total_votes": 7612.0, "dem_candidate": "Bill Ritter Jr./ Barbara O'Brien", "rep_candidate": "Bob Beauprez/ Janet Rowland", "margin": 589.0, "margin_pct": 7.930523764642521, "winner": "REP", "color": "R"}, {"county": "Otero", "dem_votes": 3432.0, "rep_votes": 2603.0, "other_votes": 146.0, "total_votes": 6181.0, "dem_candidate": "Bill Ritter Jr./ Barbara O'Brien", "rep_candidate": "Bob Beauprez/ Janet Rowland", "margin": -829.0, "margin_pct": -13.736536868268434, "winner": "DEM", "color": "D"}, {"county": "Ouray", "dem_votes": 1289.0, "rep_votes": 916.0, "other_votes": 74.0, "total_votes": 2279.0, "dem_candidate": "Bill Ritter Jr./ Barbara O'Brien", "rep_candidate": "Bob Beauprez/ Janet Rowland", "margin": -373.0, "margin_pct": -16.916099773242628, "winner": "DEM", "color": "D"}, {"county": "Park", "dem_votes": 3208.0, "rep_votes": 3301.0, "other_votes": 283.0, "total_votes": 6792.0, "dem_candidate": "Bill Ritter Jr./ Barbara O'Brien", "rep_candidate": "Bob Beauprez/ Janet Rowland", "margin": 93.0, "margin_pct": 1.4287909049009064, "winner": "REP", "color": "R"}, {"county": "Phillips", "dem_votes": 773.0, "rep_votes": 998.0, "other_votes": 30.0, "total_votes": 1801.0, "dem_candidate": "Bill Ritter Jr./ Barbara O'Brien", "rep_candidate": "Bob Beauprez/ Janet Rowland", "margin": 225.0, "margin_pct": 12.704686617730095, "winner": "REP", "color": "R"}, {"county": "Pitkin", "dem_votes": 5095.0, "rep_votes": 1428.0, "other_votes": 169.0, "total_votes": 6692.0, "dem_candidate": "Bill Ritter Jr./ Barbara O'Brien", "rep_candidate": "Bob Beauprez/ Janet Rowland", "margin": -3667.0, "margin_pct": -56.21646481680208, "winner": "DEM", "color": "D"}, {"county": "Prowers", "dem_votes": 1549.0, "rep_votes": 1688.0, "other_votes": 69.0, "total_votes": 3306.0, "dem_candidate": "Bill Ritter Jr./ Barbara O'Brien", "rep_candidate": "Bob Beauprez/ Janet Rowland", "margin": 139.0, "margin_pct": 4.294099474822366, "winner": "REP", "color": "R"}, {"county": "Pueblo", "dem_votes": 34968.0, "rep_votes": 16103.0, "other_votes": 970.0, "total_votes": 52041.0, "dem_candidate": "Bill Ritter Jr./ Barbara O'Brien", "rep_candidate": "Bob Beauprez/ Janet Rowland", "margin": -18865.0, "margin_pct": -36.938771514166554, "winner": "DEM", "color": "D"}, {"county": "Rio Blanco", "dem_votes": 773.0, "rep_votes": 1305.0, "other_votes": 74.0, "total_votes": 2152.0, "dem_candidate": "Bill Ritter Jr./ Barbara O'Brien", "rep_candidate": "Bob Beauprez/ Janet Rowland", "margin": 532.0, "margin_pct": 25.601539942252167, "winner": "REP", "color": "R"}, {"county": "Rio Grande", "dem_votes": 2284.0, "rep_votes": 1885.0, "other_votes": 93.0, "total_votes": 4262.0, "dem_candidate": "Bill Ritter Jr./ Barbara O'Brien", "rep_candidate": "Bob Beauprez/ Janet Rowland", "margin": -399.0, "margin_pct": -9.570640441352843, "winner": "DEM", "color": "D"}, {"county": "Routt", "dem_votes": 5172.0, "rep_votes": 2452.0, "other_votes": 190.0, "total_votes": 7814.0, "dem_candidate": "Bill Ritter Jr./ Barbara O'Brien", "rep_candidate": "Bob Beauprez/ Janet Rowland", "margin": -2720.0, "margin_pct": -35.67681007345226, "winner": "DEM", "color": "D"}, {"county": "Saguache", "dem_votes": 1356.0, "rep_votes": 632.0, "other_votes": 90.0, "total_votes": 2078.0, "dem_candidate": "Bill Ritter Jr./ Barbara O'Brien", "rep_candidate": "Bob Beauprez/ Janet Rowland", "margin": -724.0, "margin_pct": -36.41851106639839, "winner": "DEM", "color": "D"}, {"county": "San Juan", "dem_votes": 255.0, "rep_votes": 114.0, "other_votes": 19.0, "total_votes": 388.0, "dem_candidate": "Bill Ritter Jr./ Barbara O'Brien", "rep_candidate": "Bob Beauprez/ Janet Rowland", "margin": -141.0, "margin_pct": -38.21138211382114, "winner": "DEM", "color": "D"}, {"county": "San Miguel", "dem_votes": 1991.0, "rep_votes": 594.0, "other_votes": 119.0, "total_votes": 2704.0, "dem_candidate": "Bill Ritter Jr./ Barbara O'Brien", "rep_candidate": "Bob Beauprez/ Janet Rowland", "margin": -1397.0, "margin_pct": -54.04255319148936, "winner": "DEM", "color": "D"}, {"county": "Sedgwick", "dem_votes": 575.0, "rep_votes": 568.0, "other_votes": 24.0, "total_votes": 1167.0, "dem_candidate": "Bill Ritter Jr./ Barbara O'Brien", "rep_candidate": "Bob Beauprez/ Janet Rowland", "margin": -7.0, "margin_pct": -0.6124234470691163, "winner": "DEM", "color": "D"}, {"county": "Summit", "dem_votes": 6683.0, "rep_votes": 2939.0, "other_votes": 300.0, "total_votes": 9922.0, "dem_candidate": "Bill Ritter Jr./ Barbara O'Brien", "rep_candidate": "Bob Beauprez/ Janet Rowland", "margin": -3744.0, "margin_pct": -38.91082934940761, "winner": "DEM", "color": "D"}, {"county": "Teller", "dem_votes": 3383.0, "rep_votes": 4981.0, "other_votes": 291.0, "total_votes": 8655.0, "dem_candidate": "Bill Ritter Jr./ Barbara O'Brien", "rep_candidate": "Bob Beauprez/ Janet Rowland", "margin": 1598.0, "margin_pct": 19.10569105691057, "winner": "REP", "color": "R"}, {"county": "Washington", "dem_votes": 672.0, "rep_votes": 1367.0, "other_votes": 44.0, "total_votes": 2083.0, "dem_candidate": "Bill Ritter Jr./ Barbara O'Brien", "rep_candidate": "Bob Beauprez/ Janet Rowland", "margin": 695.0, "margin_pct": 34.085335948994604, "winner": "REP", "color": "R"}, {"county": "Weld", "dem_votes": 32677.0, "rep_votes": 32499.0, "other_votes": 2381.0, "total_votes": 67557.0, "dem_candidate": "Bill Ritter Jr./ Barbara O'Brien", "rep_candidate": "Bob Beauprez/ Janet Rowland", "margin": -178.0, "margin_pct": -0.2731066650300724, "winner": "DEM", "color": "D"}, {"county": "Yuma", "dem_votes": 1339.0, "rep_votes": 2287.0, "other_votes": 68.0, "total_votes": 3694.0, "dem_candidate": "Bill Ritter Jr./ Barbara O'Brien", "rep_candidate": "Bob Beauprez/ Janet Rowland", "margin": 948.0, "margin_pct": 26.144511858797575, "winner": "REP", "color": "R"}]}